SMTPEmail/SMTPEmail.py
SMTPEmail/__init__.py
SMTPEmail-0.4.1.dist-info/LICENSE
SMTPEmail-0.4.1.dist-info/METADATA
SMTPEmail-0.4.1.dist-info/WHEEL
SMTPEmail-0.4.1.dist-info/top_level.txt
SMTPEmail-0.4.1.dist-info/RECORD
