Metadata-Version: 2.1
Name: SMTPEmail
Version: 0.4.1
Summary: Send MIME messages via SMTP server and retrieve messages via POP3 and IMAP
Home-page: https://github.com/Weizhang2017/SMTPEmail
Author: Zhang Wei
Author-email: zhangw1.2011@gmail.com
License: UNKNOWN
Platform: UNKNOWN
Classifier: Programming Language :: Python :: 3
Classifier: Operating System :: OS Independent
